ideally/__init__.py
ideally-0.1.0.dist-info/LICENSE
ideally-0.1.0.dist-info/METADATA
ideally-0.1.0.dist-info/WHEEL
ideally-0.1.0.dist-info/top_level.txt
ideally-0.1.0.dist-info/RECORD
